neural_net_checklist-1.1.0.dist-info/METADATA
neural_net_checklist-1.1.0.dist-info/WHEEL
neural_net_checklist-1.1.0.dist-info/licenses/LICENSE
neural_net_checklist/__init__.py
neural_net_checklist/tests/__init__.py
neural_net_checklist/tests/test_torch_diagnostics.py
neural_net_checklist/torch_diagnostics.py
neural_net_checklist-1.1.0.dist-info/RECORD
