Metadata-Version: 2.1
Name: neural_net_checklist
Version: 1.1.0
Summary: A ready-to-use implementation of Andrei Karpathhy's "recipe for training neural networks"
Author-Email: Andreas Kirsch <blackhc@gmail.com>
License: MIT
Requires-Python: >=3.10
Requires-Dist: torch>=2.4.0
Requires-Dist: pytest>=8.3.2
Requires-Dist: numpy>=2.0.1
Requires-Dist: tqdm>=4.66.5
Requires-Dist: pillow>=10.4.0
Requires-Dist: torchvision>=0.19.0
